test_toolbox/__init__.py
test_toolbox/retry.py
test_toolbox/retry_test.py
test_toolbox/timer.py
test_toolbox/timer_test.py
test_toolbox-0.1.0.dist-info/LICENSE
test_toolbox-0.1.0.dist-info/METADATA
test_toolbox-0.1.0.dist-info/WHEEL
test_toolbox-0.1.0.dist-info/top_level.txt
test_toolbox-0.1.0.dist-info/RECORD
